AsperaSRAgetter/__init__.py
AsperaSRAgetter/getparser.py
AsperaSRAgetter/getsra.py
AsperaSRAgetter-2.2.dist-info/METADATA
AsperaSRAgetter-2.2.dist-info/WHEEL
AsperaSRAgetter-2.2.dist-info/entry_points.txt
AsperaSRAgetter-2.2.dist-info/top_level.txt
AsperaSRAgetter-2.2.dist-info/RECORD
