Metadata-Version: 2.1
Name: AsperaSRAgetter
Version: 2.2
Summary: The AsperaSRAgetter provides a easy way to download sequencing data from ENA by using Aspera.
Home-page: https://github.com/RunJiaJi/AsperaSRAgetter
Author: Runjia Ji
Author-email: jirunjia@gmail.com
Classifier: Programming Language :: Python :: 3.9
Classifier: Programming Language :: Python :: 3.10
Classifier: License :: OSI Approved :: MIT License
Classifier: Operating System :: POSIX :: Linux
Requires-Dist: pandas
Requires-Dist: requests
